raiden_webui/__init__.py
raiden_webui/ui/3rdpartylicenses.txt
raiden_webui/ui/MaterialIcons-Regular.4674f8ded773cb03e824.eot
raiden_webui/ui/MaterialIcons-Regular.5e7382c63da0098d634a.ttf
raiden_webui/ui/MaterialIcons-Regular.83bebaf37c09c7e1c3ee.woff
raiden_webui/ui/MaterialIcons-Regular.cff684e59ffb052d72cb.woff2
raiden_webui/ui/favicon.ico
raiden_webui/ui/index.html
raiden_webui/ui/main-es2015.5883dfe059accccfb7e4.js
raiden_webui/ui/main-es5.5883dfe059accccfb7e4.js
raiden_webui/ui/polyfills-es2015.2915d4c9f4877b4ea373.js
raiden_webui/ui/polyfills-es5.104f82986adb88f1ad21.js
raiden_webui/ui/roboto-mono-v7-latin-300.0d9638572c6457b39df8.svg
raiden_webui/ui/roboto-mono-v7-latin-300.430dc1b584f87a61b00c.woff
raiden_webui/ui/roboto-mono-v7-latin-300.708b1118e067e156826d.ttf
raiden_webui/ui/roboto-mono-v7-latin-300.b58fe0a64ccce109363f.eot
raiden_webui/ui/roboto-mono-v7-latin-300.cffc3888295f3de3e5b7.woff2
raiden_webui/ui/roboto-mono-v7-latin-regular.1ed72cb00dc79e545eb2.woff
raiden_webui/ui/roboto-mono-v7-latin-regular.27d4380fadf20e01f8e4.svg
raiden_webui/ui/roboto-mono-v7-latin-regular.298a994c1950f1238b75.eot
raiden_webui/ui/roboto-mono-v7-latin-regular.ef03309f1498ba3c92a1.ttf
raiden_webui/ui/roboto-mono-v7-latin-regular.fe990f0633a16121db07.woff2
raiden_webui/ui/roboto-v20-latin-300.37a7069dc30fc663c878.woff2
raiden_webui/ui/roboto-v20-latin-300.865f928cbabcc9f8f2b5.woff
raiden_webui/ui/roboto-v20-latin-300.8d38ed813cbcb5a0397b.eot
raiden_webui/ui/roboto-v20-latin-300.991f795de66ec216a1f8.svg
raiden_webui/ui/roboto-v20-latin-300.f1bae4d457b2415e5d7e.ttf
raiden_webui/ui/roboto-v20-latin-500.59a26cdb73eb203025db.eot
raiden_webui/ui/roboto-v20-latin-500.9024e4c16d0f988f4848.svg
raiden_webui/ui/roboto-v20-latin-500.abcf7cd8c9dfb7a3dc42.ttf
raiden_webui/ui/roboto-v20-latin-500.cea99d3e3e13a3a599a0.woff
raiden_webui/ui/roboto-v20-latin-500.f5b74d7ffcdf85b9dd60.woff2
raiden_webui/ui/roboto-v20-latin-700.2267169ee7270a22a963.woff
raiden_webui-1.2.1.dist-info/LICENSE
raiden_webui-1.2.1.dist-info/METADATA
raiden_webui-1.2.1.dist-info/WHEEL
raiden_webui-1.2.1.dist-info/top_level.txt
raiden_webui-1.2.1.dist-info/RECORD
