Metadata-Version: 2.1
Name: raiden-webui
Version: 1.2.1
Summary: Raiden webui
Home-page: https://github.com/raiden-network/webui
Author: Brainbot Labs Est.
Author-email: contact@brainbot.li
License: MIT
Keywords: raiden webui
Platform: UNKNOWN
Classifier: Development Status :: 3 - Alpha
Classifier: Intended Audience :: Developers
Classifier: License :: OSI Approved :: MIT License
Classifier: Natural Language :: English
Requires-Python: >=3.6
